{"ProjectBreakpoints":"{\"Value\":{\"Main.xaml\":[{\"ConditionalExpression\":null,\"ActionExpression\":null,\"ExpectedHitCounter\":null,\"ShouldContinueAfterAction\":false,\"BreakpointType\":1,\"LocationIdentifier\":\"Log Message\",\"IsEnabled\":true,\"Annotation\":null,\"Id\":\"58d4e724-a433-4267-8e80-14d66d75c64c\",\"ActivityIdRef\":\"LogMessage_1\",\"ActivityId\":\"1.27\",\"ActivityName\":\"Log Message\",\"IsTransient\":false}]},\"CodeBreakpoints\":{}}","Compiler":"2","ProjectWatches":"{\"Value\":[{\"Id\":\"dadb50df-42fd-4bb2-9fee-a313c530891b\",\"Expression\":\"list_cells(0)(0).Get(\\\"innerText\\\")\",\"Type\":0},{\"Id\":\"cba1e7a1-af41-4b20-95aa-c66502ab3f35\",\"Expression\":\"SudokuGame_.matrixSudoku\",\"Type\":0},{\"Id\":\"f657470c-c281-43b7-b6fd-2521e1cfbc09\",\"Expression\":\"cellOpts.ToList()[0]\",\"Type\":0},{\"Id\":\"67226a16-1c59-4c98-826d-022f5cc79664\",\"Expression\":\"cellOpts.ToList()[1]\",\"Type\":0},{\"Id\":\"f8a978ab-eec8-4125-bf51-f6a53b20a019\",\"Expression\":\"emptyCells[0]\",\"Type\":0},{\"Id\":\"4fe7661c-b964-4b88-95b8-1bf9c6d937d1\",\"Expression\":\"emptyCells[1]\",\"Type\":0},{\"Id\":\"31530833-d372-449e-90b5-91a50b56a968\",\"Expression\":\"matrixSudoku[cell.x][i]\",\"Type\":0},{\"Id\":\"cc5b4904-0c18-4800-8f28-e6af8ceaaef6\",\"Expression\":\"cell.x\",\"Type\":0},{\"Id\":\"024fa75a-3fec-4305-aee7-ba6efe7adabe\",\"Expression\":\"SudokuGame_.globalMatrixSudoku\",\"Type\":0},{\"Id\":\"0641ce2d-8f2c-4020-bb64-f94cc1da1cf0\",\"Expression\":\"SudokuGame_.originalMatrixSudoku\",\"Type\":0}]}","OpenedDocuments":"[{\"DocumentPath\":\"Main.xaml\",\"FactoryId\":\"{ACB8E7BA-F093-44C1-9B50-33ECA51AAE16}\"}]","ProjectActivitiesViewState":"{\"Main.xaml\":[{\"ActivityIdRef\":\"ForEach`1_1\",\"IsAdvancedOptionsExpanded\":false,\"Categories\":{\"\":true},\"Widgets\":{\"Body\":{\"ShowExpanded\":true}}},{\"ActivityIdRef\":\"InterruptibleWhile_1\",\"IsAdvancedOptionsExpanded\":false,\"Categories\":{\"\":true},\"Widgets\":{\"Body\":{\"ShowExpanded\":true}}},{\"ActivityIdRef\":\"LogMessage_1\",\"IsAdvancedOptionsExpanded\":false,\"Widgets\":{}},{\"ActivityIdRef\":\"ForEach`1_2\",\"IsAdvancedOptionsExpanded\":false,\"Categories\":{\"\":true},\"Widgets\":{\"Body\":{\"ShowExpanded\":true}}},{\"ActivityIdRef\":\"ForEach`1_3\",\"IsAdvancedOptionsExpanded\":false,\"Categories\":{\"\":true},\"Widgets\":{\"Body\":{\"ShowExpanded\":true}}},{\"ActivityIdRef\":\"If_1\",\"IsAdvancedOptionsExpanded\":false,\"Widgets\":{\"Then\":{\"ShowExpanded\":true},\"Else\":{\"ShowExpanded\":true}}}]}"}